deluxe/__init__.py
deluxe-0.0.0.dist-info/LICENSE
deluxe-0.0.0.dist-info/METADATA
deluxe-0.0.0.dist-info/WHEEL
deluxe-0.0.0.dist-info/top_level.txt
deluxe-0.0.0.dist-info/RECORD
