Metadata-Version: 2.1
Name: deluxe
Version: 0.0.0
Summary: Deluxe configuration management
Home-page: UNKNOWN
Author: Bulat Bochkariov
Author-email: bulat+pypi@bochkariov.com
License: MIT
Platform: UNKNOWN
Classifier: Programming Language :: Python :: 3 :: Only
Classifier: Development Status :: 1 - Planning
Classifier: License :: OSI Approved :: MIT License
Classifier: Intended Audience :: Developers
Classifier: Topic :: Software Development :: Libraries
Classifier: Operating System :: OS Independent
